field_match/.DS_Store
field_match/__init__.py
field_match/field_match.py
field_match-0.1.0.dist-info/METADATA
field_match-0.1.0.dist-info/WHEEL
field_match-0.1.0.dist-info/licenses/LICENSE
field_match-0.1.0.dist-info/RECORD
