Metadata-Version: 2.1
Name: field_match
Version: 0.1.0
Summary: Identify corresponding fields between datasets
Project-URL: Homepage, https://github.com/cstirry/field-match
Author-email: Christine Stirrat <christine.stirrat@gmail.com>
License-File: LICENSE
Classifier: License :: OSI Approved :: MIT License
Classifier: Operating System :: OS Independent
Classifier: Programming Language :: Python :: 3
Requires-Python: >=3.8
